setup.py
prob_distributions/__init__.py
prob_distributions/binomial_distributions.py
prob_distributions/general_distributions.py
prob_distributions/guassian_distributions.py
prob_distributions.egg-info/PKG-INFO
prob_distributions.egg-info/SOURCES.txt
prob_distributions.egg-info/dependency_links.txt
prob_distributions.egg-info/not-zip-safe
prob_distributions.egg-info/top_level.txt