Metadata-Version: 1.0
Name: prob-distributions
Version: 0.1
Summary: Guassian and Binomial distributions
Home-page: UNKNOWN
Author: Karvendhan
Author-email: karvsmech@gmail.com
License: UNKNOWN
Platform: UNKNOWN
